[
  {
    "id": "5154a556-dad9-4a06-8780-a2b3764d4f90",
    "data": [
      {
        "text": "bored",
        "userDefined": false
      }
    ],
    "isTemplate": false,
    "count": 0,
    "updated": 0
  },
  {
    "id": "cce6664b-784f-4e93-89c3-c3fa5b62720b",
    "data": [
      {
        "text": "boring",
        "meta": "@sys.ignore",
        "userDefined": false
      }
    ],
    "isTemplate": false,
    "count": 0,
    "updated": 0
  },
  {
    "id": "770fe28b-964f-4537-9ef5-ab0f40d1480d",
    "data": [
      {
        "text": "it bores me",
        "userDefined": false
      }
    ],
    "isTemplate": false,
    "count": 0,
    "updated": 0
  },
  {
    "id": "dc9f2d14-6970-4377-a050-f7f2db761f78",
    "data": [
      {
        "text": "that was ",
        "userDefined": false
      },
      {
        "text": "boring",
        "meta": "@sys.ignore",
        "userDefined": false
      }
    ],
    "isTemplate": false,
    "count": 0,
    "updated": 0
  },
  {
    "id": "fb48af3e-a86f-4af6-ade0-b988a014945e",
    "data": [
      {
        "text": "this is ",
        "userDefined": false
      },
      {
        "text": "boring",
        "meta": "@sys.ignore",
        "userDefined": false
      }
    ],
    "isTemplate": false,
    "count": 0,
    "updated": 0
  },
  {
    "id": "717bec95-80b5-412f-accf-16594aeddabd",
    "data": [
      {
        "text": "I\u0027m bored",
        "userDefined": false
      }
    ],
    "isTemplate": false,
    "count": 0,
    "updated": 0
  },
  {
    "id": "188e7ef5-909d-4f32-afc9-d26e548b4438",
    "data": [
      {
        "text": "very ",
        "userDefined": false
      },
      {
        "text": "boring",
        "meta": "@sys.ignore",
        "userDefined": false
      }
    ],
    "isTemplate": false,
    "count": 0,
    "updated": 0
  },
  {
    "id": "0993eef4-f267-4c59-a13d-a8de2296503e",
    "data": [
      {
        "text": "I am getting bored",
        "userDefined": false
      }
    ],
    "isTemplate": false,
    "count": 0,
    "updated": 0
  }
]