[
  {
    "id": "0a6a98bd-610b-4e95-b521-6bbec6c5593f",
    "data": [
      {
        "text": "I\u0027m insomniac",
        "userDefined": false
      }
    ],
    "isTemplate": false,
    "count": 0,
    "updated": 0
  },
  {
    "id": "417d54b2-f231-4662-a7f4-09aa777c8117",
    "data": [
      {
        "text": "I can\u0027t ",
        "userDefined": false
      },
      {
        "text": "fall",
        "meta": "@sys.ignore",
        "userDefined": false
      },
      {
        "text": " asleep",
        "userDefined": false
      }
    ],
    "isTemplate": false,
    "count": 0,
    "updated": 0
  },
  {
    "id": "3be0766b-b630-440d-b0b2-27a0017ebcef",
    "data": [
      {
        "text": "I can\u0027t ",
        "userDefined": false
      },
      {
        "text": "sleep",
        "meta": "@sys.ignore",
        "userDefined": false
      }
    ],
    "isTemplate": false,
    "count": 0,
    "updated": 0
  },
  {
    "id": "4916f991-de28-4e89-bc4d-71b04b2f5203",
    "data": [
      {
        "text": "I can\u0027t get to sleep",
        "userDefined": false
      }
    ],
    "isTemplate": false,
    "count": 0,
    "updated": 0
  },
  {
    "id": "5c3cf35b-90b0-480e-b47f-50915b613bc4",
    "data": [
      {
        "text": "I can\u0027t get no sleep",
        "userDefined": false
      }
    ],
    "isTemplate": false,
    "count": 0,
    "updated": 0
  },
  {
    "id": "e22e8674-911c-4f7d-871b-bc8325e45760",
    "data": [
      {
        "text": "I\u0027",
        "userDefined": false
      },
      {
        "text": "m",
        "meta": "@sys.ignore",
        "userDefined": false
      },
      {
        "text": " insomnious",
        "userDefined": false
      }
    ],
    "isTemplate": false,
    "count": 0,
    "updated": 0
  },
  {
    "id": "41502f92-4890-4cc3-8836-739561ad37d9",
    "data": [
      {
        "text": "I can\u0027t get any sleep",
        "userDefined": false
      }
    ],
    "isTemplate": false,
    "count": 0,
    "updated": 0
  },
  {
    "id": "3d1cea90-47a7-4f28-80a2-34f51a36f439",
    "data": [
      {
        "text": "I\u0027",
        "userDefined": false
      },
      {
        "text": "m",
        "meta": "@sys.ignore",
        "userDefined": false
      },
      {
        "text": " sleepless",
        "userDefined": false
      }
    ],
    "isTemplate": false,
    "count": 0,
    "updated": 0
  }
]