[
  {
    "id": "3724c182-e0f6-4b7e-870c-d26ddec8cbdc",
    "data": [
      {
        "text": "I came back",
        "userDefined": false
      }
    ],
    "isTemplate": false,
    "count": 0,
    "updated": 0
  },
  {
    "id": "a02d567a-14e8-475b-8b74-ab3b862cadca",
    "data": [
      {
        "text": "I got back",
        "userDefined": false
      }
    ],
    "isTemplate": false,
    "count": 0,
    "updated": 0
  },
  {
    "id": "28e7b830-d9f2-44a6-a7be-6798cfbf293d",
    "data": [
      {
        "text": "here I am again",
        "userDefined": false
      }
    ],
    "isTemplate": false,
    "count": 0,
    "updated": 0
  },
  {
    "id": "22b8bada-2a27-4ca7-ab9f-9dd8d45c1ed5",
    "data": [
      {
        "text": "I am back",
        "userDefined": false
      }
    ],
    "isTemplate": false,
    "count": 0,
    "updated": 0
  },
  {
    "id": "a502d9b3-3d12-4709-a048-9a07a03aa925",
    "data": [
      {
        "text": "I\u0027m here again",
        "userDefined": false
      }
    ],
    "isTemplate": false,
    "count": 0,
    "updated": 0
  },
  {
    "id": "2449e631-95c9-405a-936a-220c48a2847b",
    "data": [
      {
        "text": "I have returned",
        "userDefined": false
      }
    ],
    "isTemplate": false,
    "count": 0,
    "updated": 0
  }
]