[
  {
    "id": "74a42923-4fdf-4095-a352-dd3e8a44fcdf",
    "data": [
      {
        "text": "not interested",
        "userDefined": false
      }
    ],
    "isTemplate": false,
    "count": 0,
    "updated": 0
  },
  {
    "id": "fae1f5f6-fc42-4602-9cfb-b16df7b35684",
    "data": [
      {
        "text": "I ",
        "userDefined": false
      },
      {
        "text": "don",
        "meta": "@sys.ignore",
        "userDefined": false
      },
      {
        "text": "\u0027t want",
        "userDefined": false
      }
    ],
    "isTemplate": false,
    "count": 0,
    "updated": 0
  },
  {
    "id": "52520b11-1737-4a88-b79e-ee438174414f",
    "data": [
      {
        "text": "I ",
        "userDefined": false
      },
      {
        "text": "don\u0027t",
        "meta": "@sys.ignore",
        "userDefined": false
      },
      {
        "text": " want to",
        "userDefined": false
      }
    ],
    "isTemplate": false,
    "count": 0,
    "updated": 0
  },
  {
    "id": "2da29d01-80bb-4c99-811a-af923e5eb796",
    "data": [
      {
        "text": "I ",
        "userDefined": false
      },
      {
        "text": "don\u0027t",
        "meta": "@sys.ignore",
        "userDefined": false
      },
      {
        "text": " think so",
        "userDefined": false
      }
    ],
    "isTemplate": false,
    "count": 0,
    "updated": 0
  },
  {
    "id": "1807f9cb-d2f7-45e9-a08d-bf5b043a7656",
    "data": [
      {
        "text": "let \u0027s not",
        "userDefined": false
      }
    ],
    "isTemplate": false,
    "count": 0,
    "updated": 0
  },
  {
    "id": "c590bb36-5167-4292-845c-6b5d4af58779",
    "data": [
      {
        "text": "don\u0027t",
        "userDefined": false
      }
    ],
    "isTemplate": false,
    "count": 0,
    "updated": 0
  },
  {
    "id": "74d1cf17-f9b7-4a26-9acd-5eb2860e6509",
    "data": [
      {
        "text": "no ",
        "userDefined": false
      },
      {
        "text": "it\u0027s",
        "meta": "@sys.ignore",
        "userDefined": false
      },
      {
        "text": " not",
        "userDefined": false
      }
    ],
    "isTemplate": false,
    "count": 0,
    "updated": 0
  },
  {
    "id": "f1d89b22-5c69-4507-a002-9aa4f6a63bcd",
    "data": [
      {
        "text": "actually no",
        "userDefined": false
      }
    ],
    "isTemplate": false,
    "count": 1,
    "updated": 0
  },
  {
    "id": "831599e9-1d62-4d88-b3a8-b42f5de7286e",
    "data": [
      {
        "text": "no do not",
        "userDefined": false
      }
    ],
    "isTemplate": false,
    "count": 0,
    "updated": 0
  },
  {
    "id": "daebd8c1-f56a-4162-b4a8-1bb834a901af",
    "data": [
      {
        "text": "thanks but no thanks",
        "userDefined": false
      }
    ],
    "isTemplate": false,
    "count": 0,
    "updated": 0
  },
  {
    "id": "0e46ef7d-40bc-4e49-af9b-3273712437d2",
    "data": [
      {
        "text": "no thank you though",
        "userDefined": false
      }
    ],
    "isTemplate": false,
    "count": 0,
    "updated": 0
  },
  {
    "id": "c3149151-26f9-4cb7-8ec2-5d5cc2311eb0",
    "data": [
      {
        "text": "no sorry",
        "userDefined": false
      }
    ],
    "isTemplate": false,
    "count": 0,
    "updated": 0
  },
  {
    "id": "5febc86c-d915-4cdb-9a41-9c5c211e3c69",
    "data": [
      {
        "text": "disagree",
        "userDefined": false
      }
    ],
    "isTemplate": false,
    "count": 0,
    "updated": 0
  },
  {
    "id": "5aca1de8-7641-4c76-8fd5-ae0c30576d05",
    "data": [
      {
        "text": "no I would not",
        "userDefined": false
      }
    ],
    "isTemplate": false,
    "count": 0,
    "updated": 0
  },
  {
    "id": "cac5ca62-9d32-452c-993f-6aab418499d2",
    "data": [
      {
        "text": "no thanks",
        "userDefined": false
      }
    ],
    "isTemplate": false,
    "count": 1,
    "updated": 0
  },
  {
    "id": "2159db42-a245-4f6d-8276-229496d30d3c",
    "data": [
      {
        "text": "no don\u0027t",
        "userDefined": false
      }
    ],
    "isTemplate": false,
    "count": 0,
    "updated": 0
  },
  {
    "id": "1b92d33b-cb44-4886-bec0-0e3e5beea551",
    "data": [
      {
        "text": "not ",
        "userDefined": false
      },
      {
        "text": "right now",
        "meta": "@sys.ignore",
        "userDefined": false
      },
      {
        "text": " thanks",
        "userDefined": false
      }
    ],
    "isTemplate": false,
    "count": 0,
    "updated": 0
  },
  {
    "id": "aee0c81c-ff74-427d-8623-87bb2575f401",
    "data": [
      {
        "text": "no forget",
        "userDefined": false
      }
    ],
    "isTemplate": false,
    "count": 0,
    "updated": 0
  },
  {
    "id": "f56d6858-e0e4-4a60-9ed0-601639af5d89",
    "data": [
      {
        "text": "not really",
        "userDefined": false
      }
    ],
    "isTemplate": false,
    "count": 1,
    "updated": 0
  },
  {
    "id": "0cbcb01e-df7a-484d-8095-517c3f2f5d2a",
    "data": [
      {
        "text": "not needed",
        "userDefined": false
      }
    ],
    "isTemplate": false,
    "count": 0,
    "updated": 0
  },
  {
    "id": "37aded24-ecf4-4195-a18e-15e044d433d0",
    "data": [
      {
        "text": "don t have a sense",
        "userDefined": false
      }
    ],
    "isTemplate": false,
    "count": 0,
    "updated": 0
  },
  {
    "id": "1ab9ae97-6c06-4694-adeb-35ce585aae96",
    "data": [
      {
        "text": "absolutely not",
        "userDefined": false
      }
    ],
    "isTemplate": false,
    "count": 1,
    "updated": 0
  },
  {
    "id": "cfdd3229-c969-40af-abc9-082d2f1f33b2",
    "data": [
      {
        "text": "absolutely no",
        "userDefined": false
      }
    ],
    "isTemplate": false,
    "count": 0,
    "updated": 0
  },
  {
    "id": "7bb3b3ec-0824-4900-be25-5f42dba9d2cd",
    "data": [
      {
        "text": "how ",
        "userDefined": false
      },
      {
        "text": "about",
        "meta": "@sys.ignore",
        "userDefined": false
      },
      {
        "text": " no",
        "userDefined": false
      }
    ],
    "isTemplate": false,
    "count": 0,
    "updated": 0
  },
  {
    "id": "568e7775-8966-4f37-9370-91515b15b1b0",
    "data": [
      {
        "text": "not ",
        "userDefined": false
      },
      {
        "text": "today",
        "meta": "@sys.ignore",
        "userDefined": false
      }
    ],
    "isTemplate": false,
    "count": 0,
    "updated": 0
  },
  {
    "id": "46edb718-9a81-4959-a5cf-73697c2edf01",
    "data": [
      {
        "text": "don",
        "meta": "@sys.ignore",
        "userDefined": false
      },
      {
        "text": "\u0027t",
        "userDefined": false
      }
    ],
    "isTemplate": false,
    "count": 0,
    "updated": 0
  },
  {
    "id": "8bb1cc98-f6c0-4fd8-acf1-b0783313b3d5",
    "data": [
      {
        "text": "definitely not",
        "userDefined": false
      }
    ],
    "isTemplate": false,
    "count": 0,
    "updated": 0
  },
  {
    "id": "ead9d5a3-d5de-4be7-a423-bcb25473e6cd",
    "data": [
      {
        "text": "no that\u0027s wrong",
        "userDefined": false
      }
    ],
    "isTemplate": false,
    "count": 0,
    "updated": 0
  },
  {
    "id": "cd01173e-45eb-4249-b469-73aa49c6962b",
    "data": [
      {
        "text": "nooo",
        "userDefined": false
      }
    ],
    "isTemplate": false,
    "count": 0,
    "updated": 0
  },
  {
    "id": "464356af-3fea-49fc-a547-78a4bdd1a9c1",
    "data": [
      {
        "text": "no but thank you",
        "userDefined": false
      }
    ],
    "isTemplate": false,
    "count": 0,
    "updated": 0
  },
  {
    "id": "5e5dc498-55e7-4e66-9423-cf14691b2556",
    "data": [
      {
        "text": "nope",
        "userDefined": false
      }
    ],
    "isTemplate": false,
    "count": 1,
    "updated": 0
  },
  {
    "id": "9838ed85-1cf2-4233-816c-3735cf0dc9ff",
    "data": [
      {
        "text": "no need thanks",
        "userDefined": false
      }
    ],
    "isTemplate": false,
    "count": 0,
    "updated": 0
  },
  {
    "id": "f5230f38-3baf-4369-97b5-28abf230f8d5",
    "data": [
      {
        "text": "no need",
        "userDefined": false
      }
    ],
    "isTemplate": false,
    "count": 0,
    "updated": 0
  },
  {
    "id": "b1f2d14e-cf62-4d98-9954-f6207cedf59e",
    "data": [
      {
        "text": "no incorrect",
        "userDefined": false
      }
    ],
    "isTemplate": false,
    "count": 0,
    "updated": 0
  },
  {
    "id": "2454d737-5fd4-4aff-8745-92a45e6e7548",
    "data": [
      {
        "text": "not at this time",
        "userDefined": false
      }
    ],
    "isTemplate": false,
    "count": 0,
    "updated": 0
  },
  {
    "id": "245ec6fa-d2aa-4676-849f-0c06f05d6bf4",
    "data": [
      {
        "text": "no actually",
        "userDefined": false
      }
    ],
    "isTemplate": false,
    "count": 1,
    "updated": 0
  },
  {
    "id": "cbf85357-a8d8-4f64-bd1e-00c68bc53829",
    "data": [
      {
        "text": "not this",
        "userDefined": false
      }
    ],
    "isTemplate": false,
    "count": 0,
    "updated": 0
  },
  {
    "id": "c6a6db98-0d17-43f5-b797-5c8a27ea0c23",
    "data": [
      {
        "text": "no ",
        "userDefined": false
      },
      {
        "text": "leave",
        "meta": "@sys.ignore",
        "userDefined": false
      },
      {
        "text": " ",
        "userDefined": false
      },
      {
        "text": "it",
        "meta": "@sys.ignore",
        "userDefined": false
      }
    ],
    "isTemplate": false,
    "count": 0,
    "updated": 0
  },
  {
    "id": "874baa6a-a1d8-4eaf-ba8a-e892ef69ec85",
    "data": [
      {
        "text": "no never",
        "userDefined": false
      }
    ],
    "isTemplate": false,
    "count": 0,
    "updated": 0
  },
  {
    "id": "c9f4f7d7-a9ca-42e1-9e68-19621ee2de97",
    "data": [
      {
        "text": "I think no",
        "userDefined": false
      }
    ],
    "isTemplate": false,
    "count": 0,
    "updated": 0
  },
  {
    "id": "53c5d7b9-1c6a-4587-b54d-34b8ddb1f90f",
    "data": [
      {
        "text": "no ",
        "userDefined": false
      },
      {
        "text": "it",
        "meta": "@sys.ignore",
        "userDefined": false
      },
      {
        "text": " isn\u0027t",
        "userDefined": false
      }
    ],
    "isTemplate": false,
    "count": 0,
    "updated": 0
  },
  {
    "id": "39f41edf-321a-4de8-a1d8-c609ce1edb28",
    "data": [
      {
        "text": "no",
        "userDefined": false
      }
    ],
    "isTemplate": false,
    "count": 0,
    "updated": 0
  },
  {
    "id": "20993a4b-5baa-4937-9785-69a7937ceeb3",
    "data": [
      {
        "text": "I disagree",
        "userDefined": false
      }
    ],
    "isTemplate": false,
    "count": 0,
    "updated": 0
  },
  {
    "id": "45030393-f3d0-4a4f-b97f-97307c78c78e",
    "data": [
      {
        "text": "apparently not",
        "userDefined": false
      }
    ],
    "isTemplate": false,
    "count": 0,
    "updated": 0
  },
  {
    "id": "765188fe-b4c1-41d4-a089-c4be3ab16d19",
    "data": [
      {
        "text": "no way",
        "userDefined": false
      }
    ],
    "isTemplate": false,
    "count": 0,
    "updated": 0
  },
  {
    "id": "4389f8bc-5dac-4a76-abb3-82f3540a1469",
    "data": [
      {
        "text": "not really no",
        "userDefined": false
      }
    ],
    "isTemplate": false,
    "count": 0,
    "updated": 0
  },
  {
    "id": "d1748ff9-6f6d-4ee5-ba68-7949555ecb2a",
    "data": [
      {
        "text": "no thanks not right now",
        "userDefined": false
      }
    ],
    "isTemplate": false,
    "count": 0,
    "updated": 0
  },
  {
    "id": "70ea3548-5168-4a84-a48a-6fba28d681c1",
    "data": [
      {
        "text": "sorry no",
        "userDefined": false
      }
    ],
    "isTemplate": false,
    "count": 0,
    "updated": 0
  },
  {
    "id": "927fbc6b-591f-405c-82f5-5cb5ad1966df",
    "data": [
      {
        "text": "not this time",
        "userDefined": false
      }
    ],
    "isTemplate": false,
    "count": 0,
    "updated": 0
  },
  {
    "id": "158ebdf2-0ef3-41d0-b283-cc0cad0d9601",
    "data": [
      {
        "text": "no ",
        "userDefined": false
      },
      {
        "text": "don\u0027",
        "meta": "@sys.ignore",
        "userDefined": false
      },
      {
        "text": "t do that",
        "userDefined": false
      }
    ],
    "isTemplate": false,
    "count": 0,
    "updated": 0
  },
  {
    "id": "22dc2763-8628-4278-8297-aac625d0290e",
    "data": [
      {
        "text": "no thank you very much",
        "userDefined": false
      }
    ],
    "isTemplate": false,
    "count": 0,
    "updated": 0
  },
  {
    "id": "65d39061-92d4-46e1-9ae2-db8c07aadab6",
    "data": [
      {
        "text": "nah",
        "userDefined": false
      }
    ],
    "isTemplate": false,
    "count": 0,
    "updated": 0
  },
  {
    "id": "0225ae2c-17cb-47a6-9bb8-3f543617e2e8",
    "data": [
      {
        "text": "I ",
        "userDefined": false
      },
      {
        "text": "don",
        "meta": "@sys.ignore",
        "userDefined": false
      },
      {
        "text": "\u0027t want that",
        "userDefined": false
      }
    ],
    "isTemplate": false,
    "count": 0,
    "updated": 0
  },
  {
    "id": "1ce7897a-f11e-434e-83b7-f6e3583b33f6",
    "data": [
      {
        "text": "no tanks",
        "userDefined": false
      }
    ],
    "isTemplate": false,
    "count": 0,
    "updated": 0
  },
  {
    "id": "f6989fcb-d23b-4568-a01f-258944bdf90d",
    "data": [
      {
        "text": "not exactly",
        "userDefined": false
      }
    ],
    "isTemplate": false,
    "count": 0,
    "updated": 0
  },
  {
    "id": "b0bf4a89-7e58-4d37-8d57-1c97f5575c4a",
    "data": [
      {
        "text": "no ",
        "userDefined": false
      },
      {
        "text": "thank you",
        "meta": "@sys.ignore",
        "userDefined": false
      },
      {
        "text": " not ",
        "userDefined": false
      },
      {
        "text": "right now",
        "meta": "@sys.ignore",
        "userDefined": false
      }
    ],
    "isTemplate": false,
    "count": 0,
    "updated": 0
  },
  {
    "id": "3be40c8c-52bf-46f1-9917-a19c1cba1d0a",
    "data": [
      {
        "text": "I say no",
        "userDefined": false
      }
    ],
    "isTemplate": false,
    "count": 0,
    "updated": 0
  },
  {
    "id": "19ffadbb-7d89-4179-818d-7ac630f0b4e0",
    "data": [
      {
        "text": "never",
        "userDefined": false
      }
    ],
    "isTemplate": false,
    "count": 0,
    "updated": 0
  },
  {
    "id": "d855a18f-98de-4c3c-aa13-075388462b38",
    "data": [
      {
        "text": "I said no",
        "userDefined": false
      }
    ],
    "isTemplate": false,
    "count": 0,
    "updated": 0
  },
  {
    "id": "1970144a-9474-4042-b9ba-d3fdcc5d1ba1",
    "data": [
      {
        "text": "no that\u0027s ",
        "userDefined": false
      },
      {
        "text": "fine",
        "meta": "@sys.ignore",
        "userDefined": false
      },
      {
        "text": " ",
        "userDefined": false
      },
      {
        "text": "thank you",
        "meta": "@sys.ignore",
        "userDefined": false
      }
    ],
    "isTemplate": false,
    "count": 0,
    "updated": 0
  },
  {
    "id": "0f13149b-8a7a-4451-9ab6-e7b029bfe6a6",
    "data": [
      {
        "text": "na",
        "userDefined": false
      }
    ],
    "isTemplate": false,
    "count": 0,
    "updated": 0
  },
  {
    "id": "daefab4e-bcb6-4cc2-bf2b-7f8370dbc2ae",
    "data": [
      {
        "text": "no I ",
        "userDefined": false
      },
      {
        "text": "don\u0027t",
        "meta": "@sys.ignore",
        "userDefined": false
      }
    ],
    "isTemplate": false,
    "count": 0,
    "updated": 0
  },
  {
    "id": "1dfa1791-143b-45c7-86f5-92bfdbb00a69",
    "data": [
      {
        "text": "nope sorry",
        "userDefined": false
      }
    ],
    "isTemplate": false,
    "count": 0,
    "updated": 0
  },
  {
    "id": "9643619c-174b-487b-9b5b-5374e0a133ea",
    "data": [
      {
        "text": "not that",
        "userDefined": false
      }
    ],
    "isTemplate": false,
    "count": 0,
    "updated": 0
  },
  {
    "id": "c97c2260-0d54-40a9-8a85-ae73fb4087af",
    "data": [
      {
        "text": "do not",
        "userDefined": false
      }
    ],
    "isTemplate": false,
    "count": 0,
    "updated": 0
  },
  {
    "id": "0ff30062-4ac2-4543-ac82-ed12e782d6ca",
    "data": [
      {
        "text": "I\u0027m not",
        "userDefined": false
      }
    ],
    "isTemplate": false,
    "count": 1,
    "updated": 0
  },
  {
    "id": "afd55f32-0ffe-4cdf-893a-a59aafedfc2b",
    "data": [
      {
        "text": "no just no",
        "userDefined": false
      }
    ],
    "isTemplate": false,
    "count": 0,
    "updated": 0
  },
  {
    "id": "6f03276e-5e6c-4111-9c5e-750d6244b191",
    "data": [
      {
        "text": "of",
        "meta": "@sys.ignore",
        "userDefined": false
      },
      {
        "text": " course not",
        "userDefined": false
      }
    ],
    "isTemplate": false,
    "count": 0,
    "updated": 0
  }
]